[
    {
        "id": 1,
        "title": "乐享湘西",
        "desc": "天门山、黄龙洞、烟雨张家界、矮寨大桥（玻璃天廊)、凤凰古城、墨戎苗寨双飞四日游",
        "price": 1999,
        "tag": "梦幻",
        "src": "/static/datas/img/1.jpg"
    },{
        "id": 2,
        "title": "万物复苏、大地回春",
        "desc": "华兴亲子营带您踏青、挖春笋、游科技馆",
        "src": "/static/datas/img/2.jpg"
    },{
        "id": 3,
        "title": "礼遇法门",
        "desc": "品味西安，感知中国",
        "price": "2580",
        "tag": "陕西",
        "src": "/static/datas/img/3.jpg"
    }
]